<?xml version="1.0" encoding="UTF-8"?>
<Body>
	<Content>
		<Sentence>
			<Participant>中新网</Participant>
			<Location>伦敦</Location>
			<Time>7月1日</Time>电英国安全官员称，有
			<Participant>证据</Participant>
			<Denoter>显示</Denoter>，
			<Location>格拉斯哥机场</Location>
			<Time>6月30日</Time>遭燃烧汽车撞击事件是一起自杀式恐怖
			<Denoter>袭击</Denoter>事件。
		</Sentence>
		<Sentence>
			<Participant>警方</Participant>称，
			<Participant>他们</Participant>
			<Denoter>认为</Denoter>这起袭击事件与伦敦29日发生的未遂汽车炸弹袭击事件有关联，已有
			<Participant>两人</Participant>在英格兰北部因与伦敦和苏格兰发生的恐怖阴谋有关而被
			<Denoter>逮捕</Denoter>。
		</Sentence>
		<Sentence>
			<Participant>警方</Participant>称，有
			<Participant>五名旁观者</Participant>在
			<Location>格拉斯哥机场</Location>袭击事件中受伤，但他们的伤势都不严重。
		</Sentence>
		<Sentence>
			英国已将其恐怖预警等级升至最高等级，
			<Participant>美国布什政府</Participant>也
			<Denoter>宣布</Denoter>在
			<Location>机场和主要交通枢纽</Location>加强安保措施。
		</Sentence>
		<Sentence>
			<Location>一辆绿色的大切诺基</Location>
			<Time>6月30日下午三点半</Time>(北京时间下午十一点半)向
			<Location>格拉斯哥机场的主停机楼</Location>撞去，大楼入口处的安全栏使
			<Participant>司机</Participant>无法驾车
			<Denoter>闯入</Denoter>繁忙的停机楼，但车首
			<Denoter>撞毁</Denoter>了玻璃门。
		</Sentence>
		<Sentence>
			<Participant>一名官员</Participant>称：[UNK]如果他
			<Denoter>闯入</Denoter>停机楼，他将使
			<Participant>数百人</Participant>
			<Denoter>丧生</Denoter>，这很明显。[UNK]
		</Sentence>
		<Sentence>
			<Participant>苏格兰警局局长威利-拉埃</Participant>称，涉案车辆中的
			<Participant>一名男子</Participant>正在医院接受治疗，他由于被严重烧伤而生命垂危。
		</Sentence>
		<Sentence>
			另一人则被
			<Participant>警方</Participant>
			<Denoter>拘留</Denoter>。
		</Sentence>
		<Sentence>
			他说，
			<Participant>警方</Participant>在那名入院男子的身上发现了一[UNK]可
			<Object>疑装置[UNK]，[UNK]可疑装置</Object>[UNK]已被
			<Denoter>带往</Denoter>一个安全地点以进行
			<Denoter>调查</Denoter>。
		</Sentence>
		<Sentence>
			<Participant>拉埃拒</Participant>绝
			<Denoter>披露</Denoter>这一装置是否是自杀式腰带。
		</Sentence>
		<Sentence>
			他说：[UNK]我可以证实，我们
			<Denoter>认为</Denoter>
			<Location>格拉斯哥机场事件与伦敦昨天</Location>
			<Time>(6月29)日</Time>发生的事件有关。
		</Sentence>
	</Content>
</Body>
