<?xml version="1.0" encoding="UTF-8"?>
<Body>
	<Content>
		<Sentence>
			<Participant>新华网</Participant>
			<Location>太原</Location>
			<Time>3月11日</Time>电(记者晏国政吕梦琦)记者
			<Time>11日20时</Time>从
			<Participant>山西省晋城市政府新闻办</Participant>
			<Denoter>获悉</Denoter>，截至
			<Time>11日10时</Time>，通过dna
			<Denoter>鉴定</Denoter>，
			<Location>二广高速晋城段岩后隧道[UNK]3・1</Location>[UNK]事故目前
			<Denoter>确认</Denoter>了16名遇难者身份。
		</Sentence>
		<Sentence>
			<Participant>有关部门</Participant>反复
			<Denoter>勘验</Denoter>调查，
			<Denoter>确认</Denoter>损毁车辆42部，
			<Location>现场</Location>有48人逃生，其中
			<Participant>1人</Participant>
			<Denoter>抢救</Denoter>无效
			<Denoter>死亡</Denoter>。
		</Sentence>
		<Sentence>
			事故发生以来，陆续有
			<Participant>群众</Participant>
			<Denoter>申报</Denoter>失踪失联人员39名。
		</Sentence>
		<Sentence>
			因
			<Location>现场</Location>情况极其复杂，
			<Denoter>确认</Denoter>遇难人数难度很大，鉴于现场搜集的
			<Object>大部分遗体残骸高度</Object>
			<Denoter>碳化</Denoter>，
			<Participant>有关专家已</Participant>
			<Denoter>赶赴</Denoter>
			<Location>现场</Location>给予技术
			<Denoter>支持</Denoter>。
		</Sentence>
		<Sentence>
			<Time>同时</Time>，
			<Participant>公安机关</Participant>已组织专门力量，通过车辆信息、户籍资料、亲属印证、同乘人员证实等措施，进一步
			<Denoter>确认</Denoter>其他失踪失联人员身份。
		</Sentence>
		<Sentence>
			<Time>1日14时50分</Time>，
			<Location>二广高速晋城段岩后隧道内</Location>
			<Object>两辆载有液态甲醇的重型罐车</Object>发生
			<Denoter>追尾</Denoter>，并引发起火爆炸。
		</Sentence>
	</Content>
</Body>
